lurrn/feature.so
lurrn/sparsmat.so
lurrn/__init__.py
lurrn/learn.so
lurrn/alphabet.so
lurrn/item_logging.py
Lurrn-1.0.0.dist-info/RECORD
Lurrn-1.0.0.dist-info/WHEEL
Lurrn-1.0.0.dist-info/METADATA
Lurrn-1.0.0.dist-info/metadata.json
Lurrn-1.0.0.dist-info/DESCRIPTION.rst
Lurrn-1.0.0.dist-info/top_level.txt
